trol/__init__.py
trol/collection.py
trol/database.py
trol/highlander.py
trol/lock.py
trol/model.py
trol/property.py
trol/util.py
trol-0.5.3.dist-info/LICENSE.txt
trol-0.5.3.dist-info/METADATA
trol-0.5.3.dist-info/WHEEL
trol-0.5.3.dist-info/top_level.txt
trol-0.5.3.dist-info/RECORD
