Metadata-Version: 2.1
Name: trol
Version: 0.5.3
Summary: A light and predictable Redis object mapper
Home-page: https://github.com/nategraf/trol
Author: Victor "Nate" Graf
Author-email: nategraf1@gmail.com
License: MIT
Keywords: redis,object,mapper,thin,rom,redisco,cache
Platform: UNKNOWN
Classifier: Development Status :: 3 - Alpha
Classifier: Intended Audience :: Developers
Classifier: Topic :: Software Development :: Build Tools
Classifier: License :: OSI Approved :: MIT License
Classifier: Operating System :: OS Independent
Classifier: Natural Language :: English
Classifier: Programming Language :: Python :: 3
Classifier: Programming Language :: Python :: 3 :: Only
Classifier: Topic :: Database
Classifier: Topic :: Software Development :: Libraries :: Python Modules
Requires-Python: >=3
License-File: LICENSE.txt
Requires-Dist: redis
